clayton/__init__.py
clayton/rng/__init__.py
clayton/rng/archimedean.py
clayton/rng/base.py
clayton/rng/elliptical.py
clayton/rng/evd.py
clayton/rng/monte_carlo.py
clayton/rng/utils.py
clayton/tests/__init__.py
clayton/tests/test_archimedean.py
clayton/tests/test_base.py
clayton/tests/test_evd.py
clayton-0.0.4.dist-info/METADATA
clayton-0.0.4.dist-info/WHEEL
clayton-0.0.4.dist-info/top_level.txt
clayton-0.0.4.dist-info/RECORD
