Metadata-Version: 2.1
Name: clayton
Version: 0.0.4
Summary: Sampling from copulae
Home-page: https://github.com/Aleboul/clayton
Download-URL: https://github.com/Aleboul/clayton/
Author: Alexis Boulin
Author-email: aboulin@unice.fr
